strivehealthchecks/__init__.py
strivehealthchecks/health_check_result.py
strivehealthchecks/health_checker.py
strivehealthchecks/py.typed
strivehealthchecks/service_health.py
strivehealthchecks-1.1.0.dist-info/METADATA
strivehealthchecks-1.1.0.dist-info/WHEEL
strivehealthchecks-1.1.0.dist-info/licenses/LICENSE
strivehealthchecks-1.1.0.dist-info/RECORD
