Metadata-Version: 2.1
Name: strivehealthchecks
Version: 1.1.0
Summary: A simple framework for running health checks.
Project-URL: Homepage, https://github.com/strivesolutions/python-health-checks
Project-URL: Bug Tracker, https://github.com/strivesolutions/python-health-checks/issues
License: MIT License
License-File: LICENSE
Requires-Python: >=3.10
Requires-Dist: asyncer>=0.0.2
